LinOT/SinkhornNP.py
LinOT/Visualization.py
LinOT/__init__.py
LinOT/auxiliary.py
LinOT-0.0.2.dist-info/LICENSE
LinOT-0.0.2.dist-info/METADATA
LinOT-0.0.2.dist-info/WHEEL
LinOT-0.0.2.dist-info/top_level.txt
LinOT-0.0.2.dist-info/RECORD
